webrtc_audio_processing/__init__.py
webrtc_audio_processing/_webrtc_audio_processing.so
webrtc_audio_processing/webrtc_audio_processing.py
webrtc_audio_processing-0.1.3.dist-info/METADATA
webrtc_audio_processing-0.1.3.dist-info/WHEEL
webrtc_audio_processing-0.1.3.dist-info/top_level.txt
webrtc_audio_processing-0.1.3.dist-info/RECORD
