Metadata-Version: 2.1
Name: webrtc_audio_processing
Version: 0.1.3
Summary: Python bindings of webrtc audio processing
Home-page: https://github.com/xiongyihui/python-webrtc-audio-processing
Author: Yihui Xiong
Author-email: yihui.xiong@hotmail.com
License: BSD
Download-URL: https://pypi.python.org/pypi/webrtc_audio_processing
Keywords: webrtc audioprocessing,voice activity detection,noise suppression,automatic gain control
Platform: Linux
Classifier: Development Status :: 2 - Pre-Alpha
Classifier: License :: OSI Approved :: BSD License
Classifier: Operating System :: POSIX :: Linux
Classifier: Programming Language :: Python :: 2
Classifier: Programming Language :: Python :: 2.6
Classifier: Programming Language :: Python :: 2.7
Classifier: Programming Language :: Python :: 3
Classifier: Programming Language :: Python :: 3.2
Classifier: Programming Language :: Python :: 3.3
Classifier: Programming Language :: Python :: 3.4
Classifier: Programming Language :: Python :: 3.5
Classifier: Programming Language :: C++
